robot_detection.py
setup.py
robot_detection.egg-info/PKG-INFO
robot_detection.egg-info/SOURCES.txt
robot_detection.egg-info/dependency_links.txt
robot_detection.egg-info/requires.txt
robot_detection.egg-info/top_level.txt